{
  "lab-1" : [{"x":0.13,"y":0.53,"width":2,"height":97},{"x":0.13,"y":97.37,"width":65,"height":2},{"x":65,"y":32.89,"width":2,"height":64},{"x":97.24,"y":0.53,"width":2,"height":99},{"x":0.13,"y":0.53,"width":32,"height":2},{"x":32.37,"y":0.53,"width":65,"height":2},{"x":32.37,"y":0.53,"width":2,"height":66}],
  "lab-2" : [{"x":0.13,"y":0.66,"width":2,"height":96},{"x":0.13,"y":96.84,"width":97,"height":2},{"x":32.37,"y":0.66,"width":65,"height":2},{"x":32.37,"y":0.66,"width":2,"height":67},{"x":32.37,"y":67.89,"width":35,"height":2},{"x":97.37,"y":32.37,"width":2,"height":64},{"x":97.37,"y":0.66,"width":2,"height":32},{"x":66.32,"y":32.37,"width":31,"height":2}],
  "lab-3" : [{"x":0.13,"y":0.53,"width":99,"height":2},{"x":0.26,"y":0.53,"width":2,"height":96},{"x":0.26,"y":96.58,"width":97,"height":2},{"x":96.84,"y":32.89,"width":2,"height":64},{"x":32.11,"y":32.89,"width":65,"height":2},{"x":32.11,"y":32.89,"width":2,"height":33},{"x":32.11,"y":66.32,"width":35,"height":2}],
  "lab-4" : [{"x":0.53,"y":0.53,"width":2,"height":97},{"x":48.82,"y":97.89,"width":26,"height":2},{"x":0.53,"y":97.89,"width":48,"height":2},{"x":48.82,"y":73.42,"width":2,"height":24},{"x":0.53,"y":0.53,"width":48,"height":2},{"x":48.88,"y":0.53,"width":48,"height":2},{"x":48.88,"y":0.53,"width":2,"height":26},{"x":25.13,"y":50,"width":2,"height":25},{"x":25.13,"y":25,"width":2,"height":24},{"x":25.13,"y":48.55,"width":2,"height":1},{"x":25.13,"y":48.55,"width":48,"height":2},{"x":72.89,"y":25,"width":2,"height":48},{"x":97.24,"y":0.53,"width":2,"height":73},{"x":97.24,"y":73.42,"width":2,"height":24},{"x":72.89,"y":73.42,"width":24,"height":2}],
  "lab-5" : [{"x":0,"y":0.39,"width":2,"height":97},{"x":0,"y":97.5,"width":97,"height":2},{"x":24.61,"y":0.39,"width":2,"height":73},{"x":24.61,"y":72.89,"width":50,"height":2},{"x":97.24,"y":48.95,"width":2,"height":49},{"x":97.24,"y":0.39,"width":2,"height":49},{"x":48.55,"y":48.95,"width":49,"height":2},{"x":48.55,"y":25,"width":2,"height":24},{"x":72.89,"y":0.39,"width":24,"height":2},{"x":24.61,"y":0.39,"width":48,"height":2},{"x":72.89,"y":0.39,"width":2,"height":26}],
  "lab-6" : [{"x":65.53,"y":32.89,"width":2,"height":32},{"x":0.66,"y":65.26,"width":65,"height":2},{"x":0.66,"y":0.39,"width":2,"height":65},{"x":96.84,"y":0.39,"width":2,"height":96},{"x":0.66,"y":96.84,"width":96,"height":2},{"x":0.66,"y":0.39,"width":31,"height":2},{"x":31.84,"y":0.39,"width":65,"height":2},{"x":31.84,"y":0.39,"width":2,"height":34}],
  "lab-7" : [{"x":-0.13,"y":0.39,"width":2,"height":99},{"x":96.97,"y":0.39,"width":2,"height":97},{"x":32.24,"y":97.24,"width":65,"height":2},{"x":32.24,"y":32.76,"width":2,"height":64},{"x":-0.13,"y":0.39,"width":65,"height":2},{"x":65,"y":0.39,"width":32,"height":2},{"x":65,"y":0.39,"width":2,"height":66}],
  "lab-8" : [{"x":24.47,"y":48.95,"width":26,"height":2},{"x":24.47,"y":24.87,"width":2,"height":24},{"x":24.47,"y":24.87,"width":48,"height":2},{"x":72.76,"y":24.87,"width":2,"height":48},{"x":0.39,"y":72.89,"width":72,"height":2},{"x":0.39,"y":0.39,"width":2,"height":73},{"x":0.39,"y":0.39,"width":97,"height":2},{"x":96.97,"y":0.39,"width":2,"height":97},{"x":0.39,"y":97.37,"width":97,"height":2}],
  "lab-9" : [{"x":97.5,"y":-0.13,"width":2,"height":100},{"x":0,"y":-0.13,"width":2,"height":97},{"x":72.89,"y":24.87,"width":2,"height":72},{"x":0,"y":97.11,"width":24,"height":2},{"x":24.34,"y":97.11,"width":49,"height":2},{"x":24.34,"y":24.87,"width":2,"height":72},{"x":48.75,"y":-0.13,"width":49,"height":2},{"x":0,"y":-0.13,"width":49,"height":2},{"x":48.75,"y":-0.13,"width":2,"height":74}],
  "lab-10" : [{"x":0.13,"y":0,"width":2,"height":97},{"x":0.13,"y":97.37,"width":97,"height":2},{"x":97.5,"y":24.61,"width":2,"height":73},{"x":48.82,"y":24.61,"width":49,"height":2},{"x":48.82,"y":24.61,"width":2,"height":26},{"x":24.47,"y":0,"width":75,"height":2},{"x":0.13,"y":0,"width":24,"height":2},{"x":24.47,"y":0,"width":2,"height":72},{"x":24.47,"y":72.37,"width":48,"height":2},{"x":72.76,"y":49.34,"width":2,"height":23}]
}